langchain_deepseek/__init__.py
langchain_deepseek/chat_models.py
langchain_deepseek/py.typed
langchain_deepseek-0.1.0.dist-info/LICENSE
langchain_deepseek-0.1.0.dist-info/METADATA
langchain_deepseek-0.1.0.dist-info/WHEEL
langchain_deepseek-0.1.0.dist-info/RECORD
